xapiparser/__init__.py
xapiparser/__main__.py
xapiparser/cli.py
xapiparser/exception.py
xapiparser/parser.py
xapiparser-0.0.15.dist-info/AUTHORS.rst
xapiparser-0.0.15.dist-info/LICENSE
xapiparser-0.0.15.dist-info/METADATA
xapiparser-0.0.15.dist-info/WHEEL
xapiparser-0.0.15.dist-info/entry_points.txt
xapiparser-0.0.15.dist-info/top_level.txt
xapiparser-0.0.15.dist-info/RECORD
