Metadata-Version: 2.1
Name: xapiparser
Version: 0.0.15
Summary: XAPI ssh command parser to convert cli commands to xml for use in the Cisco XAPI REST API
Home-page: https://github.com/jonathanelscpt/xapiparser
Author: Jonathan Els
Author-email: jonathanelscpt@gmail.com
License: MIT
Project-URL: Changelog, https://github.com/jonathanelscpt/xapiparser/blob/master/CHANGELOG.rst
Project-URL: Issue Tracker, https://github.com/jonathanelscpt/xapiparser/issues
Keywords: cisco,xapi,telepresence,telepresence,collaboration endpoint software
Platform: UNKNOWN
Classifier: Development Status :: 3 - Alpha
Classifier: Intended Audience :: Developers
Classifier: License :: OSI Approved :: MIT License
Classifier: Operating System :: Unix
Classifier: Operating System :: POSIX
Classifier: Operating System :: Microsoft :: Windows
Classifier: Programming Language :: Python
Classifier: Programming Language :: Python :: 3
Classifier: Programming Language :: Python :: 3.6
Classifier: Programming Language :: Python :: 3.7
Classifier: Programming Language :: Python :: 3.8
Classifier: Programming Language :: Python :: 3.9
Classifier: Programming Language :: Python :: Implementation :: CPython
Classifier: Programming Language :: Python :: Implementation :: PyPy
Classifier: Topic :: Utilities
Classifier: Topic :: Text Processing :: Markup :: XML
Classifier: Topic :: Communications :: Telephony
Requires-Python: >=3.6
Requires-Dist: lxml
